helloworld.py
nalirpy-0.0.1.dist-info/LICENSE.txt
nalirpy-0.0.1.dist-info/METADATA
nalirpy-0.0.1.dist-info/WHEEL
nalirpy-0.0.1.dist-info/top_level.txt
nalirpy-0.0.1.dist-info/RECORD
